agentstudio/__init__.py
agentstudio/cli.py
agentstudio/components/__init__.py
agentstudio/components/forms.py
agentstudio/components/sidebar.py
agentstudio/custom_tools/__init__.py
agentstudio/custom_tools/arxiv_search.py
agentstudio/custom_tools/arxiv_search_meta.json
agentstudio/hawkins_agent/__init__.py
agentstudio/hawkins_agent/agent.py
agentstudio/hawkins_agent/types.py
agentstudio/hawkins_agent/llm/__init__.py
agentstudio/hawkins_agent/llm/provider.py
agentstudio/hawkins_agent/mock/__init__.py
agentstudio/hawkins_agent/mock/document.py
agentstudio/hawkins_agent/mock/knowledge_base.py
agentstudio/tools/rag_tool.py
agentstudio/utils/__init__.py
agentstudio/utils/agent_manager.py
agentstudio/utils/database.py
agentstudio/utils/file_handler.py
agentstudio/utils/flow_manager.py
agentstudio/utils/rag_manager.py
agentstudio/utils/templates.py
agentstudio/utils/workflow_manager.py
agentstudio/web/agents.json
agentstudio/web/agents.json.lock
agentstudio/web/api.py
agentstudio/web/hawkins_memory.db
agentstudio/web/hawkins_rag.db
agentstudio/web/main.py
agentstudio/web/workflows.json
agentstudio/web/.streamlit/config.toml
agentstudio/web/custom_tools/arxiv_search.py
agentstudio/web/custom_tools/arxiv_search_meta.json
agentstudio/web/custom_tools/reverse_tool.py
agentstudio/web/custom_tools/reverse_tool_meta.json
agentstudio/web/pages/__init__.py
agentstudio/web/pages/create_agent.py
agentstudio/web/pages/create_workflow.py
agentstudio/web/pages/settings.py
agentstudio/web/pages/test_playground.py
agentstudio/web/pages/tool_editor.py
agentstudio/web/pages/tutorial.py
agentstudio/web/pages/workflow_builder.py
agent_studio-0.1.7.dist-info/METADATA
agent_studio-0.1.7.dist-info/WHEEL
agent_studio-0.1.7.dist-info/entry_points.txt
agent_studio-0.1.7.dist-info/RECORD
