Metadata-Version: 2.4
Name: agent-studio
Version: 0.1.7
Summary: No-code AI agent creation platform with Streamlit UI and FastAPI backend
Project-URL: Documentation, https://github.com/username/agent-studio#readme
Project-URL: Source, https://github.com/username/agent-studio
Author: Harish Santhanalakshmi Ganesan
License: MIT
Requires-Python: >=3.11
Requires-Dist: aiofiles>=24.1.0
Requires-Dist: anthropic>=0.37.1
Requires-Dist: asyncio>=3.4.3
Requires-Dist: build>=1.2.2.post1
Requires-Dist: chardet>=5.2.0
Requires-Dist: click>=8.1.0
Requires-Dist: fastapi>=0.115.2
Requires-Dist: filelock>=3.17.0
Requires-Dist: hawkins-agent<=0.1.7
Requires-Dist: hawkins-rag>=0.1.0
Requires-Dist: hawkinsdb>=1.0.1
Requires-Dist: langchain>=0.3.18
Requires-Dist: openai>=1.62.0
Requires-Dist: pip>=25.0.1
Requires-Dist: psutil>=5.9.8
Requires-Dist: pypdf2>=3.0.1
Requires-Dist: python-multipart>=0.0.20
Requires-Dist: requests>=2.32.3
Requires-Dist: streamlit-agraph>=0.0.45
Requires-Dist: streamlit-flow-component
Requires-Dist: streamlit>=1.42.0
Requires-Dist: trafilatura>=2.0.0
Requires-Dist: twilio>=9.4.5
Requires-Dist: twine>=6.1.0
Requires-Dist: uvicorn>=0.34.0
